[
  {
    "trial_id": 0,
    "hyperparameters": {
      "batch_size": 128,
      "learning_rate": 0.0005,
      "n_layers": 2,
      "units": 64,
      "dropout": 0.0,
      "embed_dim": 64,
      "filters": 128,
      "kernel_size": 3
    },
    "val_recall": 0.7045454545454546,
    "epochs": 20,
    "batch_size": 128
  },
  {
    "trial_id": 1,
    "hyperparameters": {
      "batch_size": 256,
      "learning_rate": 0.001,
      "n_layers": 1,
      "units": 128,
      "dropout": 0.2,
      "embed_dim": 64,
      "filters": 128,
      "kernel_size": 5
    },
    "val_recall": 0.7045454545454546,
    "epochs": 20,
    "batch_size": 256
  },
  {
    "trial_id": 2,
    "hyperparameters": {
      "batch_size": 256,
      "learning_rate": 0.0005,
      "n_layers": 2,
      "units": 64,
      "dropout": 0.2,
      "embed_dim": 64,
      "filters": 64,
      "kernel_size": 5
    },
    "val_recall": 0.7045454545454546,
    "epochs": 20,
    "batch_size": 256
  },
  {
    "trial_id": 3,
    "hyperparameters": {
      "batch_size": 128,
      "learning_rate": 0.001,
      "n_layers": 2,
      "units": 128,
      "dropout": 0.2,
      "embed_dim": 64,
      "filters": 64,
      "kernel_size": 5
    },
    "val_recall": 0.7045454545454546,
    "epochs": 20,
    "batch_size": 128
  },
  {
    "trial_id": 4,
    "hyperparameters": {
      "batch_size": 256,
      "learning_rate": 0.001,
      "n_layers": 1,
      "units": 64,
      "dropout": 0.0,
      "embed_dim": 64,
      "filters": 128,
      "kernel_size": 5
    },
    "val_recall": 0.7045454545454546,
    "epochs": 20,
    "batch_size": 256
  }
]